scientiflow_xtbsa/__init__.py
scientiflow_xtbsa/cli.py
scientiflow_xtbsa/plot_report.py
scientiflow_xtbsa/run_xtb.py
scientiflow_xtbsa/sampling.py
scientiflow_xtbsa-0.1.2.dist-info/LICENSE.md
scientiflow_xtbsa-0.1.2.dist-info/METADATA
scientiflow_xtbsa-0.1.2.dist-info/WHEEL
scientiflow_xtbsa-0.1.2.dist-info/entry_points.txt
scientiflow_xtbsa-0.1.2.dist-info/RECORD
