Metadata-Version: 2.1
Name: scientiflow-xtbsa
Version: 0.1.2
Summary: Semi-QM ensemble rescoring and xTB/ALPB binding energy analysis toolkit.
License: LICENSE.md
Author: ScientiFlow
Author-email: scientiflow@gmail.com
Requires-Python: >=3.12
Classifier: License :: Other/Proprietary License
Classifier: Programming Language :: Python :: 3
Classifier: Programming Language :: Python :: 3.12
Requires-Dist: click (>=8.1,<8.2)
Requires-Dist: matplotlib (>=3.9,<4.0)
Requires-Dist: mdanalysis (>=2.6,<3.0)
Requires-Dist: numpy (>=2.0,<3.0)
Requires-Dist: pandas (>=2.2,<3.0)
Requires-Dist: rich (>=13.7,<14.0)
Requires-Dist: scikit-learn (>=1.5,<2.0)
Requires-Dist: typer (>=0.12,<0.13)
